uptime_kuma_mcp_server/__init__.py
uptime_kuma_mcp_server/__main__.py
uptime_kuma_mcp_server/server.py
uptime_kuma_mcp_server-0.1.15.dist-info/METADATA
uptime_kuma_mcp_server-0.1.15.dist-info/WHEEL
uptime_kuma_mcp_server-0.1.15.dist-info/entry_points.txt
uptime_kuma_mcp_server-0.1.15.dist-info/RECORD
