Metadata-Version: 2.4
Name: uptime-kuma-mcp-server
Version: 0.1.15
Summary: Uptime Kuma MCP Server for managing monitors
Project-URL: Homepage, https://github.com/camusama/uptime-kuma-mcp-server
Author-email: Marquez Yang <marquez.yang@foxmail.com>
License: MIT
Classifier: Development Status :: 4 - Beta
Classifier: Intended Audience :: Developers
Classifier: License :: OSI Approved :: MIT License
Classifier: Programming Language :: Python :: 3
Classifier: Programming Language :: Python :: 3.10
Requires-Python: >=3.10
Requires-Dist: mcp[cli]>=1.6.0
Requires-Dist: python-dotenv>=0.9.9
Requires-Dist: uptime-kuma-api>=1.2.1
